qwix/__init__.py
qwix/pallas.py
qwix/_src/aux_data.py
qwix/_src/averaging.py
qwix/_src/flax_util.py
qwix/_src/interception.py
qwix/_src/model.py
qwix/_src/qconfig.py
qwix/_src/core/conv_general.py
qwix/_src/core/conv_general_qt.py
qwix/_src/core/dot.py
qwix/_src/core/dot_general.py
qwix/_src/core/dot_general_qt.py
qwix/_src/core/einsum.py
qwix/_src/core/numerics.py
qwix/_src/core/pallas.py
qwix/_src/core/qarray.py
qwix/_src/core/ragged_dot.py
qwix/_src/core/ragged_dot_qt.py
qwix/_src/core/stochastic_rounding.py
qwix/_src/providers/lora.py
qwix/_src/providers/odml.py
qwix/_src/providers/odml_ops.py
qwix/_src/providers/ptq.py
qwix/_src/providers/qt.py
qwix/contrib/gptq.py
qwix/contrib/gptq_core.py
qwix/contrib/padded_ptq.py
qwix-0.1.5.dist-info/licenses/LICENSE
qwix-0.1.5.dist-info/METADATA
qwix-0.1.5.dist-info/WHEEL
qwix-0.1.5.dist-info/top_level.txt
qwix-0.1.5.dist-info/RECORD
